datacrunch/InferenceClient/__init__.py
datacrunch/InferenceClient/inference_client.py
datacrunch/__init__.py
datacrunch/authentication/__init__.py
datacrunch/authentication/authentication.py
datacrunch/balance/__init__.py
datacrunch/balance/balance.py
datacrunch/constants.py
datacrunch/containers/__init__.py
datacrunch/containers/containers.py
datacrunch/datacrunch.py
datacrunch/exceptions.py
datacrunch/helpers.py
datacrunch/http_client/__init__.py
datacrunch/http_client/http_client.py
datacrunch/images/__init__.py
datacrunch/images/images.py
datacrunch/instance_types/__init__.py
datacrunch/instance_types/instance_types.py
datacrunch/instances/__init__.py
datacrunch/instances/instances.py
datacrunch/locations/__init__.py
datacrunch/locations/locations.py
datacrunch/ssh_keys/__init__.py
datacrunch/ssh_keys/ssh_keys.py
datacrunch/startup_scripts/__init__.py
datacrunch/startup_scripts/startup_scripts.py
datacrunch/volume_types/__init__.py
datacrunch/volume_types/volume_types.py
datacrunch/volumes/__init__.py
datacrunch/volumes/volumes.py
datacrunch-1.19.0.dist-info/WHEEL
datacrunch-1.19.0.dist-info/METADATA
datacrunch-1.19.0.dist-info/RECORD
